openforis_whisp/__init__.py
openforis_whisp/data_conversion.py
openforis_whisp/datasets.py
openforis_whisp/logger.py
openforis_whisp/parameters/__init__.py
openforis_whisp/parameters/config_runtime.py
openforis_whisp/parameters/lookup_context_and_metadata.csv
openforis_whisp/parameters/lookup_gee_datasets.csv
openforis_whisp/pd_schemas.py
openforis_whisp/reformat.py
openforis_whisp/risk.py
openforis_whisp/stats.py
openforis_whisp/utils.py
openforis_whisp-0.0.1.dist-info/LICENSE
openforis_whisp-0.0.1.dist-info/METADATA
openforis_whisp-0.0.1.dist-info/WHEEL
openforis_whisp-0.0.1.dist-info/RECORD
