Metadata-Version: 2.3
Name: openforis-whisp
Version: 0.0.1
Summary: Whisp (What is in that plot) is an open-source solution which helps to produce relevant forest monitoring information and support compliance with deforestation-related regulations.
License: MIT
Keywords: whisp,geospatial,data-processing
Author: Andy Arnell
Author-email: and.arnell@fao.org
Requires-Python: >=3.10
Classifier: Development Status :: 3 - Alpha
Classifier: Intended Audience :: Developers
Classifier: Intended Audience :: Science/Research
Classifier: License :: OSI Approved :: MIT License
Classifier: Programming Language :: Python :: 3
Classifier: Programming Language :: Python :: 3.10
Classifier: Programming Language :: Python :: 3.11
Classifier: Programming Language :: Python :: 3.12
Classifier: Programming Language :: Python :: 3.13
Classifier: Topic :: Software Development :: Libraries :: Python Modules
Requires-Dist: country_converter (>=0.7,<2.0.0)
Requires-Dist: earthengine-api
Requires-Dist: geemap
Requires-Dist: geojson (>=2.5.0,<3.0.0)
Requires-Dist: ipykernel (>=6.17.1,<7.0.0)
Requires-Dist: numpy (>=1.21.0,<3.0.0)
Requires-Dist: pandas (>=1.3.0,<3.0.0)
Requires-Dist: pandera[io] (>=0.22.1,<1.0.0)
Requires-Dist: pydantic-core (>=2.14.0,<3.0.0)
Requires-Dist: python-dotenv (>=1.0.1,<2.0.0)
Requires-Dist: rsa (>=4.2,<5.0.0)
Requires-Dist: shapely (>=2.0.2,<3.0.0)
